qset/__init__.py
qset/client.py
qset/test_client.py
qset/utils/__init__.py
qset/utils/builtin/VERSION
qset/utils/builtin/__init__.py
qset/utils/builtin/collection.py
qset/utils/coder/VERSION
qset/utils/coder/__init__.py
qset/utils/coder/binary.py
qset/utils/coder/coder.py
qset/utils/coder/coders/__init__.py
qset/utils/coder/coders/json/__init__.py
qset/utils/coder/coders/json/json_coder.py
qset/utils/coder/coders/msgpack/__init__.py
qset/utils/coder/coders/msgpack/msgpack_coder.py
qset/utils/coder/coders/test_coder.py
qset/utils/numeric/VERSION
qset/utils/numeric/__init__.py
qset/utils/numeric/numeric.py
qset/utils/numeric/types.py
qset/utils/pandas_writer/PandasCSVWriter.py
qset/utils/pandas_writer/VERSION
qset/utils/pandas_writer/__init__.py
qset/utils/split_file/VERSION
qset/utils/split_file/__init__.py
qset/utils/split_file/split_file.py
qset/utils/time/VERSION
qset/utils/time/__init__.py
qset/utils/time/dt.py
qset/utils/time/ranges.py
qset/utils/tqdm/VERSION
qset/utils/tqdm/__init__.py
qset/utils/tqdm/tqdm_tools.py
qset_python_client-0.1.6.dist-info/LICENSE
qset_python_client-0.1.6.dist-info/WHEEL
qset_python_client-0.1.6.dist-info/METADATA
qset_python_client-0.1.6.dist-info/RECORD
