Metadata-Version: 2.1
Name: qset-python-client
Version: 0.1.6
Summary: Python client for Qset API
License: MIT
Author: akadaner
Author-email: arseniikadaner@gmail.com
Requires-Python: >=3.7.1,<4.0.0
Classifier: License :: OSI Approved :: MIT License
Classifier: Programming Language :: Python :: 3
Classifier: Programming Language :: Python :: 3.8
Classifier: Programming Language :: Python :: 3.9
Requires-Dist: Delorean (>=1.0.0,<2.0.0)
Requires-Dist: PyYAML (>=5.4.1,<6.0.0)
Requires-Dist: msgpack (>=1.0.0,<2.0.0)
Requires-Dist: pandas (>=1.1.3,<2.0.0)
Requires-Dist: requests (>=2.24.0,<3.0.0)
Requires-Dist: tenacity (>=6.2.0,<7.0.0)
Requires-Dist: tqdm (>=4.50.2,<5.0.0)
Requires-Dist: ujson (>=4.0.2,<5.0.0)
